odoo/addons/sale_coupon_multi_currency/README.rst
odoo/addons/sale_coupon_multi_currency/__init__.py
odoo/addons/sale_coupon_multi_currency/__manifest__.py
odoo/addons/sale_coupon_multi_currency/i18n/fr.po
odoo/addons/sale_coupon_multi_currency/i18n/sale_coupon_multi_currency.pot
odoo/addons/sale_coupon_multi_currency/models/__init__.py
odoo/addons/sale_coupon_multi_currency/models/sale_coupon_program.py
odoo/addons/sale_coupon_multi_currency/readme/CONTRIBUTORS.rst
odoo/addons/sale_coupon_multi_currency/readme/DESCRIPTION.rst
odoo/addons/sale_coupon_multi_currency/static/description/icon.png
odoo/addons/sale_coupon_multi_currency/static/description/index.html
odoo/addons/sale_coupon_multi_currency/tests/__init__.py
odoo/addons/sale_coupon_multi_currency/tests/common.py
odoo/addons/sale_coupon_multi_currency/tests/test_sale_coupon_multi_currency.py
odoo/addons/sale_coupon_multi_currency/views/sale_coupon_program_views.xml
odoo13_addon_sale_coupon_multi_currency-13.0.1.0.3.dist-info/METADATA
odoo13_addon_sale_coupon_multi_currency-13.0.1.0.3.dist-info/WHEEL
odoo13_addon_sale_coupon_multi_currency-13.0.1.0.3.dist-info/top_level.txt
odoo13_addon_sale_coupon_multi_currency-13.0.1.0.3.dist-info/RECORD
